Makefile
README.rst
setup.py
docs/Makefile
docs/make.bat
docs/source/HISTORY.rst
docs/source/README.rst
docs/source/conf.py
scripts/api-sample.py
scripts/out.txt
scripts/sample.zip
xmldirector/__init__.py
xmldirector.bookalope.egg-info/PKG-INFO
xmldirector.bookalope.egg-info/SOURCES.txt
xmldirector.bookalope.egg-info/dependency_links.txt
xmldirector.bookalope.egg-info/entry_points.txt
xmldirector.bookalope.egg-info/namespace_packages.txt
xmldirector.bookalope.egg-info/not-zip-safe
xmldirector.bookalope.egg-info/requires.txt
xmldirector.bookalope.egg-info/top_level.txt
xmldirector/bookalope/__init__.py
xmldirector/bookalope/configure.zcml
xmldirector/bookalope/header.txt
xmldirector/bookalope/i18n.py
xmldirector/bookalope/interfaces.py
xmldirector/bookalope/logger.py
xmldirector/bookalope/browser/__init__.py
xmldirector/bookalope/browser/api.py
xmldirector/bookalope/browser/bookalope.pt
xmldirector/bookalope/browser/bookalope.py
xmldirector/bookalope/browser/configure.zcml
xmldirector/bookalope/browser/controlpanel.py
xmldirector/bookalope/browser/restapi.py
xmldirector/bookalope/browser/view.py
xmldirector/bookalope/locales/LC_MESSAGES/de/README.txt
xmldirector/bookalope/profiles/default/README.txt
xmldirector/bookalope/profiles/default/browserlayer.xml
xmldirector/bookalope/profiles/default/controlpanel.xml
xmldirector/bookalope/profiles/default/metadata.xml
xmldirector/bookalope/profiles/default/registry.xml
xmldirector/bookalope/profiles/default/types.xml
xmldirector/bookalope/profiles/default/types/xmldirector.plonecore.connector.xml