Metadata-Version: 1.1
Name: xmldirector.bookalope
Version: 0.3.2
Summary: Plone/XML-Director integration with bookalope.net
Home-page: http://pypi.python.org/pypi/xmldirector.bookalope
Author: Andreas Jung
Author-email: info@zopyx.com
License: GPL
Keywords: xml-director bookalope XML Plone Python ebooks
Platform: UNKNOWN
Classifier: Programming Language :: Python
Classifier: Framework :: Plone
Classifier: Framework :: Plone :: 4.3
Classifier: Framework :: Plone :: 5.0
Classifier: Framework :: Zope2
Classifier: Topic :: Software Development :: Libraries :: Python Modules
